{
  "typeCheckingMode": "standard",
  "venvPath": ".",
  "venv": ".venv",
  "reportMissingImports": true,
  "reportMissingTypeStubs": false,
  "reportUnusedImport": true,
  "reportUnusedVariable": true,
  "reportUnusedClass": true,
  "reportUnusedFunction": true,
  "reportDuplicateImport": true,
  "reportOptionalSubscript": true,
  "reportOptionalMemberAccess": true,
  "reportOptionalCall": true,
  "reportOptionalIterable": true,
  "reportOptionalContextManager": true,
  "reportOptionalOperand": true,
  "reportUntypedFunctionDecorator": true,
  "reportUntypedClassDecorator": true,
  "reportUntypedBaseClass": true,
  "reportUntypedNamedTuple": true,
  "reportPrivateUsage": true,
  "reportConstantRedefinition": true,
  "reportIncompatibleMethodOverride": true,
  "reportIncompatibleVariableOverride": true,
  "reportInconsistentConstructor": true,
  "reportOverlappingOverloads": true,
  "reportMissingParameterType": true,
  "reportMissingTypeArgument": true,
  "reportInvalidStringEscapeSequence": true,
  "reportUnknownParameterType": true,
  "reportUnknownArgumentType": true,
  "reportUnknownLambdaType": true,
  "reportUnknownVariableType": true,
  "reportUnknownMemberType": true,
  "reportMissingTypeArgument": true,
  "reportUnnecessaryIsInstance": true,
  "reportUnnecessaryCast": true,
  "reportUnnecessaryComparison": true,
  "reportAssertAlwaysTrue": true,
  "reportSelfClsParameterName": true,
  "reportImplicitStringConcatenation": true,
  "reportUndefinedVariable": true,
  "reportUnboundVariable": true,
  "reportDuplicateImport": true,
  "reportWildcardImportFromLibrary": true,
  "reportConstantRedefinition": true,
  "reportIncompatibleMethodOverride": true,
  "reportIncompatibleVariableOverride": true,
  "reportInconsistentConstructor": true,
  "reportOverlappingOverloads": true,
  "reportMissingParameterType": true,
  "reportMissingTypeArgument": true,
  "reportInvalidStringEscapeSequence": true,
  "reportUnknownParameterType": true,
  "reportUnknownArgumentType": true,
  "reportUnknownLambdaType": true,
  "reportUnknownVariableType": true,
  "reportUnknownMemberType": true,
  "reportMissingTypeArgument": true,
  "reportUnnecessaryIsInstance": true,
  "reportUnnecessaryCast": true,
  "reportUnnecessaryComparison": true,
  "reportAssertAlwaysTrue": true,
  "reportSelfClsParameterName": true,
  "reportImplicitStringConcatenation": true,
  "reportUndefinedVariable": true,
  "reportUnboundVariable": true,
  "reportDuplicateImport": true,
  "reportWildcardImportFromLibrary": true
}
